jhconverter/converter.py
ppt_to_pdf_converter-0.0.3.dist-info/LICENSE
ppt_to_pdf_converter-0.0.3.dist-info/METADATA
ppt_to_pdf_converter-0.0.3.dist-info/WHEEL
ppt_to_pdf_converter-0.0.3.dist-info/top_level.txt
ppt_to_pdf_converter-0.0.3.dist-info/RECORD
